asyncj/__init__.py
asyncj/asyncj.py
asyncj/syncj.py
asyncj-1.1.4.dist-info/LICENSE
asyncj-1.1.4.dist-info/METADATA
asyncj-1.1.4.dist-info/WHEEL
asyncj-1.1.4.dist-info/top_level.txt
asyncj-1.1.4.dist-info/RECORD
