Metadata-Version: 2.1
Name: asyncj
Version: 1.1.4
Summary: Python module for fast asynchronous work with JSON files
Home-page: https://github.com/VengDevs/AsyncJ
Author: VengDevs
License: MIT License
Keywords: async json
Classifier: Programming Language :: Python :: 3.8
Classifier: License :: OSI Approved :: MIT License
Classifier: Operating System :: OS Independent
Requires-Python: >=3.8
License-File: LICENSE
Requires-Dist: aiofiles
Requires-Dist: ujson
